app/__init__.py
app/logic.py
app/main.py
app/mcp_service.py
app/teable_api_client.py
python_app_demo-1.7.2.dist-info/METADATA
python_app_demo-1.7.2.dist-info/WHEEL
python_app_demo-1.7.2.dist-info/entry_points.txt
python_app_demo-1.7.2.dist-info/top_level.txt
python_app_demo-1.7.2.dist-info/RECORD
