Metadata-Version: 2.4
Name: python-app-demo
Version: 1.7.2
Summary: 示例 Python 项目，通过 logging 输出简单信息。
Author: baiyx
License: MIT
Requires-Python: >=3.10
Requires-Dist: mcp>=1.6.0
Requires-Dist: pydantic>=2.0.0
Requires-Dist: requests>=2.31.0
Provides-Extra: dev
Requires-Dist: pytest>=8.0; extra == "dev"
Dynamic: requires-python
